ManufaiTest/__init__.py
ManufaiUnityTesting/__init__.py
ManufaiTest-0.1.1.dist-info/LICENCE.txt
ManufaiTest-0.1.1.dist-info/METADATA
ManufaiTest-0.1.1.dist-info/WHEEL
ManufaiTest-0.1.1.dist-info/top_level.txt
ManufaiTest-0.1.1.dist-info/RECORD
